my_middleware/__init__.py
my_middleware/middleware.py
my_middleware-0.32.dist-info/METADATA
my_middleware-0.32.dist-info/WHEEL
my_middleware-0.32.dist-info/top_level.txt
my_middleware-0.32.dist-info/RECORD
