Metadata-Version: 2.1
Name: my_middleware
Version: 0.32
Summary: A Flask middleware package to perform pre-checks before request execution.
Home-page: https://github.com/vishwaranjankumar2000/my_middleware
Author: Vishwaranjan Kumar
Author-email: vishwaranjan.kumar@infoobjects.com
Classifier: Programming Language :: Python :: 3
Classifier: License :: OSI Approved :: MIT License
Classifier: Operating System :: OS Independent
Requires-Python: >=3.6
Requires-Dist: Flask >=2.0.0
